infi.diskmanagement-0.3.16-py2.7-nspkg.pth
infi/diskmanagement/__init__.py
infi/diskmanagement/__version__.py
infi/diskmanagement/disk/__init__.py
infi/diskmanagement/ioctl/__init__.py
infi/diskmanagement/ioctl/constants.py
infi/diskmanagement/ioctl/structures.py
infi/diskmanagement/ioctl/tests.py
infi/diskmanagement/mount_manager/__init__.py
infi/diskmanagement/mount_manager/tests.py
infi/diskmanagement/wmi/__init__.py
infi/diskmanagement/wmi/model/__init__.py
infi/diskmanagement/wmi/model/tests.py
infi/diskmanagement/wmi/tests/__init__.py
infi.diskmanagement-0.3.16.dist-info/LICENSE
infi.diskmanagement-0.3.16.dist-info/METADATA
infi.diskmanagement-0.3.16.dist-info/WHEEL
infi.diskmanagement-0.3.16.dist-info/entry_points.txt
infi.diskmanagement-0.3.16.dist-info/namespace_packages.txt
infi.diskmanagement-0.3.16.dist-info/top_level.txt
infi.diskmanagement-0.3.16.dist-info/RECORD
